{
   "emd":{
      "version":2,
      "currentTime":"2015-06-17T20:20:02Z",
      "name":"history",
      "key":"typeID,regionID,date",
      "columns":"typeID,regionID,date,lowPrice,highPrice,avgPrice,volume,orders",
      "result":[
         {
            "row":{
               "typeID":"18",
               "regionID":"10000002",
               "date":"2015-05-19",
               "lowPrice":"50.11",
               "highPrice":"51.81",
               "avgPrice":"51.76",
               "volume":"16522871",
               "orders":"141"
            }
         },
         {
            "row":{
               "typeID":"18",
               "regionID":"10000002",
               "date":"2015-05-20",
               "lowPrice":"50.5",
               "highPrice":"51",
               "avgPrice":"50.5",
               "volume":"13281812",
               "orders":"158"
            }
         },
         {
            "row":{
               "typeID":"18",
               "regionID":"10000002",
               "date":"2015-05-21",
               "lowPrice":"51.08",
               "highPrice":"55.5",
               "avgPrice":"52.46",
               "volume":"17046586",
               "orders":"147"
            }
         },
         {
            "row":{
               "typeID":"18",
               "regionID":"10000002",
               "date":"2015-05-22",
               "lowPrice":"50.11",
               "highPrice":"51.08",
               "avgPrice":"50.11",
               "volume":"12375294",
               "orders":"113"
            }
         },
         {
            "row":{
               "typeID":"18",
               "regionID":"10000002",
               "date":"2015-05-23",
               "lowPrice":"54.5",
               "highPrice":"55.79",
               "avgPrice":"54.5",
               "volume":"49637600",
               "orders":"102"
            }
         },
         {
            "row":{
               "typeID":"18",
               "regionID":"10000002",
               "date":"2015-05-24",
               "lowPrice":"53.16",
               "highPrice":"53.16",
               "avgPrice":"53.16",
               "volume":"23801621",
               "orders":"153"
            }
         },
         {
            "row":{
               "typeID":"18",
               "regionID":"10000002",
               "date":"2015-05-25",
               "lowPrice":"53.28",
               "highPrice":"53.33",
               "avgPrice":"53.33",
               "volume":"18708132",
               "orders":"175"
            }
         },
         {
            "row":{
               "typeID":"18",
               "regionID":"10000002",
               "date":"2015-05-26",
               "lowPrice":"50.15",
               "highPrice":"53.42",
               "avgPrice":"53.41",
               "volume":"12162739",
               "orders":"119"
            }
         },
         {
            "row":{
               "typeID":"18",
               "regionID":"10000002",
               "date":"2015-05-28",
               "lowPrice":"50.13",
               "highPrice":"53.52",
               "avgPrice":"53.49",
               "volume":"22574568",
               "orders":"85"
            }
         },
         {
            "row":{
               "typeID":"18",
               "regionID":"10000002",
               "date":"2015-05-29",
               "lowPrice":"50.16",
               "highPrice":"53.72",
               "avgPrice":"53.54",
               "volume":"6225140",
               "orders":"97"
            }
         },
         {
            "row":{
               "typeID":"18",
               "regionID":"10000002",
               "date":"2015-05-30",
               "lowPrice":"50.16",
               "highPrice":"53.9",
               "avgPrice":"53.8",
               "volume":"13102144",
               "orders":"150"
            }
         },
         {
            "row":{
               "typeID":"18",
               "regionID":"10000002",
               "date":"2015-05-31",
               "lowPrice":"50.15",
               "highPrice":"54.28",
               "avgPrice":"54.25",
               "volume":"6766049",
               "orders":"131"
            }
         },
         {
            "row":{
               "typeID":"18",
               "regionID":"10000002",
               "date":"2015-06-01",
               "lowPrice":"50.14",
               "highPrice":"54.37",
               "avgPrice":"54.32",
               "volume":"5880408",
               "orders":"119"
            }
         },
         {
            "row":{
               "typeID":"18",
               "regionID":"10000002",
               "date":"2015-06-02",
               "lowPrice":"52.99",
               "highPrice":"55",
               "avgPrice":"54.65",
               "volume":"20988367",
               "orders":"107"
            }
         },
         {
            "row":{
               "typeID":"18",
               "regionID":"10000002",
               "date":"2015-06-03",
               "lowPrice":"50.15",
               "highPrice":"54.71",
               "avgPrice":"54.67",
               "volume":"4193294",
               "orders":"82"
            }
         },
         {
            "row":{
               "typeID":"18",
               "regionID":"10000002",
               "date":"2015-06-04",
               "lowPrice":"50.15",
               "highPrice":"50.15",
               "avgPrice":"50.15",
               "volume":"14897302",
               "orders":"105"
            }
         },
         {
            "row":{
               "typeID":"18",
               "regionID":"10000002",
               "date":"2015-06-05",
               "lowPrice":"54.61",
               "highPrice":"54.77",
               "avgPrice":"54.64",
               "volume":"13918432",
               "orders":"111"
            }
         },
         {
            "row":{
               "typeID":"18",
               "regionID":"10000002",
               "date":"2015-06-06",
               "lowPrice":"54.61",
               "highPrice":"54.61",
               "avgPrice":"54.61",
               "volume":"8898754",
               "orders":"131"
            }
         },
         {
            "row":{
               "typeID":"18",
               "regionID":"10000002",
               "date":"2015-06-07",
               "lowPrice":"53.29",
               "highPrice":"53.3",
               "avgPrice":"53.3",
               "volume":"9755537",
               "orders":"142"
            }
         },
         {
            "row":{
               "typeID":"18",
               "regionID":"10000002",
               "date":"2015-06-08",
               "lowPrice":"53.3",
               "highPrice":"53.3",
               "avgPrice":"53.3",
               "volume":"9785093",
               "orders":"114"
            }
         },
         {
            "row":{
               "typeID":"18",
               "regionID":"10000002",
               "date":"2015-06-09",
               "lowPrice":"53.3",
               "highPrice":"53.3",
               "avgPrice":"53.3",
               "volume":"27114563",
               "orders":"134"
            }
         },
         {
            "row":{
               "typeID":"18",
               "regionID":"10000002",
               "date":"2015-06-10",
               "lowPrice":"54.8",
               "highPrice":"54.8",
               "avgPrice":"54.8",
               "volume":"18494588",
               "orders":"163"
            }
         },
         {
            "row":{
               "typeID":"18",
               "regionID":"10000002",
               "date":"2015-06-11",
               "lowPrice":"46.1",
               "highPrice":"53.29",
               "avgPrice":"50.16",
               "volume":"3532737",
               "orders":"98"
            }
         },
         {
            "row":{
               "typeID":"18",
               "regionID":"10000002",
               "date":"2015-06-12",
               "lowPrice":"46.21",
               "highPrice":"53.29",
               "avgPrice":"53.28",
               "volume":"25196640",
               "orders":"128"
            }
         },
         {
            "row":{
               "typeID":"18",
               "regionID":"10000002",
               "date":"2015-06-13",
               "lowPrice":"53.29",
               "highPrice":"53.29",
               "avgPrice":"53.29",
               "volume":"8185002",
               "orders":"141"
            }
         },
         {
            "row":{
               "typeID":"18",
               "regionID":"10000002",
               "date":"2015-06-14",
               "lowPrice":"53.29",
               "highPrice":"53.29",
               "avgPrice":"53.29",
               "volume":"12375153",
               "orders":"154"
            }
         },
         {
            "row":{
               "typeID":"18",
               "regionID":"10000002",
               "date":"2015-06-15",
               "lowPrice":"46.15",
               "highPrice":"58.26",
               "avgPrice":"54.38",
               "volume":"2250157",
               "orders":"38"
            }
         }
      ]
   }
}